async_pycatbox/__init__.py
async_pycatbox/async_pycatbox.py
async_pycatbox-1.1.3.dist-info/LICENSE.md
async_pycatbox-1.1.3.dist-info/METADATA
async_pycatbox-1.1.3.dist-info/WHEEL
async_pycatbox-1.1.3.dist-info/top_level.txt
async_pycatbox-1.1.3.dist-info/RECORD
