Metadata-Version: 2.1
Name: async-pycatbox
Version: 1.1.3
Summary: Async version of pycatbox, a Python API wrapper for catbox.moe.
Home-page: https://github.com/challos/async_pycatbox
Author: Andrew McGrail
Author-email: andrewjerrismcgrail@gmail.com
License: Apache License, Version 2.0, see LICENSE file
License-File: LICENSE.md
Requires-Dist: aiohttp
